trustrag/__init__.py
trustrag/version.py
trustrag/applications/__init__.py
trustrag/applications/rag.py
trustrag/applications/rag_multimodal.py
trustrag/applications/rag_openai.py
trustrag/applications/rag_openai_bge.py
trustrag/applications/rag_weibo.py
trustrag/applications/rerank.py
trustrag/applications/rewriter.py
trustrag/modules/document/__init__.py
trustrag/modules/document/base.py
trustrag/modules/document/chunk.py
trustrag/modules/document/common_parser.py
trustrag/modules/document/docx_parser.py
trustrag/modules/document/excel_parser.py
trustrag/modules/document/html_parser.py
trustrag/modules/document/huqie.txt
trustrag/modules/document/huqie.txt.trie
trustrag/modules/document/json_parser.py
trustrag/modules/document/markdown_parser.py
trustrag/modules/document/pdf_mineru_parser.py
trustrag/modules/document/pdf_parser_fast.py
trustrag/modules/document/ppt_parser.py
trustrag/modules/document/rag_tokenizer.py
trustrag/modules/document/txt_parser.py
trustrag/modules/document/utils.py
trustrag-0.0.15.dist-info/METADATA
trustrag-0.0.15.dist-info/WHEEL
trustrag-0.0.15.dist-info/top_level.txt
trustrag-0.0.15.dist-info/RECORD
